griff/__init__.py
griff/__main__.py
griff/abstract_entry_point.py
griff/domain/__init__.py
griff/domain/abstract_domain_factory.py
griff/domain/abstract_entity.py
griff/domain/auto_vo/__init__.py
griff/domain/auto_vo/abstract_aggregate_root.py
griff/domain/auto_vo/auto_entity_id_vo.py
griff/domain/auto_vo/base_value_object.py
griff/domain/auto_vo/constraints/__init__.py
griff/domain/auto_vo/constraints/abstract_constraint.py
griff/domain/auto_vo/constraints/base_constraint/__init__.py
griff/domain/auto_vo/constraints/base_constraint/decimal.py
griff/domain/auto_vo/constraints/base_constraint/integer.py
griff/domain/auto_vo/constraints/base_constraint/list.py
griff/domain/auto_vo/constraints/base_constraint/string.py
griff/domain/auto_vo/constraints/cloudinary_url.py
griff/domain/auto_vo/constraints/date_constraints.py
griff/domain/auto_vo/constraints/email.py
griff/domain/auto_vo/constraints/in_enum.py
griff/domain/auto_vo/constraints/length.py
griff/domain/auto_vo/constraints/list_length.py
griff/domain/auto_vo/constraints/min_max.py
griff/domain/auto_vo/constraints/of_type.py
griff/domain/auto_vo/constraints/phone_number.py
griff/domain/auto_vo/constraints/positive.py
griff/domain/auto_vo/constraints/primary_id.py
griff/domain/auto_vo/constraints/required.py
griff/domain/auto_vo/constraints/url.py
griff/domain/auto_vo/constraints/uuid_constraint.py
griff/domain/auto_vo/decimal_vo.py
griff/domain/auto_vo/enum_vo.py
griff/domain/auto_vo/generic_factory.py
griff/domain/auto_vo/integer_vo.py
griff/domain/auto_vo/service_map.py
griff/domain/auto_vo/string_vo.py
griff/domain/auto_vo/tests_facilities/__init__.py
griff/domain/auto_vo/tests_facilities/aggregates_test_mixin.py
griff/domain/auto_vo/tests_facilities/fake_generic_factory.py
griff/domain/auto_vo/user_permission_vo.py
griff/domain/auto_vo/uuid_vo.py
griff/domain/business_invariant_decorator.py
griff/domain/common_domain_exceptions.py
griff/domain/common_opcodes.py
griff/domain/domain_error_handler.py
griff-1.0.0.dist-info/METADATA
griff-1.0.0.dist-info/WHEEL
griff-1.0.0.dist-info/entry_points.txt
griff-1.0.0.dist-info/RECORD
