Metadata-Version: 2.1
Name: griff
Version: 1.0.0
Summary: 
Author: Wedge Digital
Requires-Python: >=3.10,<4.0
Classifier: Programming Language :: Python :: 3
Classifier: Programming Language :: Python :: 3.10
Classifier: Programming Language :: Python :: 3.11
Classifier: Programming Language :: Python :: 3.12
Classifier: Programming Language :: Python :: 3.13
Requires-Dist: aiopath (<4)
Requires-Dist: aioshutil (>=1.3,<2.0)
Requires-Dist: aiosql (>=10.1,<11.0)
Requires-Dist: aiosqlite (>=0.20.0,<0.21.0)
Requires-Dist: arrow (>=1.3.0,<2.0.0)
Requires-Dist: asyncpg (>=0.29.0,<0.30.0)
Requires-Dist: docxtpl (>=0.16.7,<0.17.0)
Requires-Dist: fastapi (>=0.110.0,<0.111.0)
Requires-Dist: fastapi-babel (>=0.0.8,<0.0.9)
Requires-Dist: flatten-json (>=0.1.14,<0.2.0)
Requires-Dist: httpx (>=0.27.0,<0.28.0)
Requires-Dist: injector (>=0.21.0,<0.22.0)
Requires-Dist: jinja2 (>=3.1.2,<4.0.0)
Requires-Dist: loguru (>=0.7.2,<0.8.0)
Requires-Dist: orjson (>=3.9.10,<4.0.0)
Requires-Dist: passlib (>=1.7.4,<2.0.0)
Requires-Dist: phonenumbers (>=8.13.27,<9.0.0)
Requires-Dist: pydantic-i18n (>=0.4.0,<0.5.0)
Requires-Dist: pydantic-settings (>=2.1.0,<3.0.0)
Requires-Dist: pydantic[email] (>=2.5.3,<3.0.0)
Requires-Dist: pyjwt (>=2.8.0,<3.0.0)
Requires-Dist: python-docx (>=1.1.0,<2.0.0)
Requires-Dist: python-dotenv (>=1.0.0,<2.0.0)
Requires-Dist: sendgrid (>=6.11.0,<7.0.0)
Requires-Dist: setuptools (>=69,<70)
Requires-Dist: typer (>=0.10.0,<0.11.0)
Requires-Dist: yoyo-migrations (>=8.2.0,<9.0.0)
